README.txt
setup.py
BrickPi/BrickPi.py
BrickPi/BrickPiScratch.py
BrickPi/__init__.py
BrickPi.egg-info/PKG-INFO
BrickPi.egg-info/SOURCES.txt
BrickPi.egg-info/dependency_links.txt
BrickPi.egg-info/requires.txt
BrickPi.egg-info/top_level.txt