Metadata-Version: 1.1
Name: BrickPi
Version: 0.1.1
Summary: BrickPi interfaces for Python and Scratch
Home-page: http://pypi.python.org/pypi/BrickPi/
Author: W. H. Bell
Author-email: whbqcd1@gmail.com
License: Creative Commons Attribution-ShareAlike 3.0
Keywords: Raspberry Pi BrickPi Scratch
Platform: UNKNOWN
Classifier: Development Status :: 3 - Alpha
Classifier: Operating System :: POSIX :: Linux
Classifier: Intended Audience :: Developers
Classifier: Programming Language :: Python :: 2.6
Classifier: Programming Language :: Python :: 2.7
Classifier: Topic :: Software Development
Classifier: Topic :: Home Automation
Classifier: Topic :: System :: Hardware
